CHANGELOG.txt
LICENCE.txt
MANIFEST.in
README.txt
__main__.py
requirements.txt
setup.py
sigma_dq/__init__.py
sigma_dq.egg-info/PKG-INFO
sigma_dq.egg-info/SOURCES.txt
sigma_dq.egg-info/dependency_links.txt
sigma_dq.egg-info/requires.txt
sigma_dq.egg-info/top_level.txt
sigma_dq/core/__init__.py
sigma_dq/core/column_operations_new.py
sigma_dq/core/sigma_dq_check_column_value_lengthCheck.py
sigma_dq/core/sigma_dq_check_customPatternCheck.py
sigma_dq/core/sigma_dq_check_endsWith.py
sigma_dq/core/sigma_dq_check_fieldCompareWithCondition.py
sigma_dq/core/sigma_dq_check_fieldCompareWithMathematicalOperations.py
sigma_dq/core/sigma_dq_check_fieldCompare_with_current_date.py
sigma_dq/core/sigma_dq_check_fieldCompare_with_current_timestamp.py
sigma_dq/core/sigma_dq_check_fieldCompare_with_field.py
sigma_dq/core/sigma_dq_check_fieldCompare_with_value.py
sigma_dq/core/sigma_dq_check_isAlphabet.py
sigma_dq/core/sigma_dq_check_isAscii.py
sigma_dq/core/sigma_dq_check_isBlank.py
sigma_dq/core/sigma_dq_check_isBoolean.py
sigma_dq/core/sigma_dq_check_isDate.py
sigma_dq/core/sigma_dq_check_isDecimal.py
sigma_dq/core/sigma_dq_check_isDecimalCond.py
sigma_dq/core/sigma_dq_check_isDuplicate.py
sigma_dq/core/sigma_dq_check_isEmail.py
sigma_dq/core/sigma_dq_check_isExisting.py
sigma_dq/core/sigma_dq_check_isExistingCond.py
sigma_dq/core/sigma_dq_check_isExistingCondAdvanced.py
sigma_dq/core/sigma_dq_check_isExisting_v1.py
sigma_dq/core/sigma_dq_check_isInList.py
sigma_dq/core/sigma_dq_check_isInListCond.py
sigma_dq/core/sigma_dq_check_isInNotList.py
sigma_dq/core/sigma_dq_check_isNegativeNumber.py
sigma_dq/core/sigma_dq_check_isNull.py
sigma_dq/core/sigma_dq_check_isNullCondition.py
sigma_dq/core/sigma_dq_check_isNumber.py
sigma_dq/core/sigma_dq_check_isPositiveNumber.py
sigma_dq/core/sigma_dq_check_isSpace.py
sigma_dq/core/sigma_dq_check_isTimestamp.py
sigma_dq/core/sigma_dq_check_isURL.py
sigma_dq/core/sigma_dq_check_isUpperCase.py
sigma_dq/core/sigma_dq_check_leadingZero.py
sigma_dq/core/sigma_dq_check_mathematicalOperationsWithColumn.py
sigma_dq/core/sigma_dq_check_startsWith.py
sigma_dq/core/sigma_dq_check_textToNumberCheck.py
