Metadata-Version: 1.1
Name: sigma-dq
Version: 0.0.7
Summary: Spark sql rules for custom rules
Home-page: UNKNOWN
Author: Prathamesh Chavan
Author-email: pratham.chavan28@gmail.com
License: MIT
Keywords: quality_checks
Platform: UNKNOWN
Classifier: Development Status :: 5 - Production/Stable
Classifier: Intended Audience :: Education
Classifier: Operating System :: Microsoft :: Windows :: Windows 10
Classifier: License :: OSI Approved :: MIT License
Classifier: Programming Language :: Python :: 3
